setup.py
arpit_distributions/Binomialdistribution.py
arpit_distributions/Gaussiandistribution.py
arpit_distributions/Generaldistribution.py
arpit_distributions/__init__.py
arpit_distributions.egg-info/PKG-INFO
arpit_distributions.egg-info/SOURCES.txt
arpit_distributions.egg-info/dependency_links.txt
arpit_distributions.egg-info/not-zip-safe
arpit_distributions.egg-info/top_level.txt